<layer>
  <name>rod_trecho_rodoviario_l</name>
  <id>LayerInfoImpl-57259db0:17d29f27fe9:-66d</id>
  <type>VECTOR</type>
  <defaultStyle>
    <id>StyleInfoImpl-57259db0:17d28bd573a:-df1</id>
  </defaultStyle>
  <resource class="featureType">
    <id>FeatureTypeInfoImpl-57259db0:17d29f27fe9:-66e</id>
  </resource>
  <attribution>
    <logoWidth>0</logoWidth>
    <logoHeight>0</logoHeight>
  </attribution>
  <dateCreated>2021-11-16 18:20:25.709 UTC</dateCreated>
  <dateModified>2021-11-16 19:55:16.949 UTC</dateModified>
</layer>