<layer>
  <name>hid_bacia_contribuicao</name>
  <id>LayerInfoImpl--6dcef4b1:17b0bec8002:-775</id>
  <type>VECTOR</type>
  <defaultStyle>
    <id>StyleInfoImpl--6dcef4b1:17b0bec8002:-75e</id>
  </defaultStyle>
  <resource class="featureType">
    <id>FeatureTypeInfoImpl--6dcef4b1:17b0bec8002:-776</id>
  </resource>
  <queryable>false</queryable>
  <attribution>
    <logoWidth>0</logoWidth>
    <logoHeight>0</logoHeight>
  </attribution>
  <dateCreated>2021-08-05 17:05:38.107 UTC</dateCreated>
  <dateModified>2021-08-05 17:12:33.584 UTC</dateModified>
</layer>