<GeoServerTileLayer>
  <id>LayerInfoImpl--1f997add:179c7e9e418:-7fbb</id>
  <enabled>true</enabled>
  <inMemoryCached>true</inMemoryCached>
  <name>jacobina:cad_secao_logradouro_l</name>
  <mimeFormats>
    <string>image/png</string>
    <string>image/jpeg</string>
  </mimeFormats>
  <gridSubsets>
    <gridSubset>
      <gridSetName>EPSG:900913</gridSetName>
      <extent>
        <coords>
          <double>-4515901.06348379</double>
          <double>-1255177.7919712008</double>
          <double>-4507920.563925284</double>
          <double>-1249174.8085836351</double>
        </coords>
      </extent>
    </gridSubset>
    <gridSubset>
      <gridSetName>EPSG:4326</gridSetName>
      <extent>
        <coords>
          <double>-40.567029468990896</double>
          <double>-11.203371841215418</double>
          <double>-40.495339421707754</double>
          <double>-11.150468917988224</double>
        </coords>
      </extent>
    </gridSubset>
  </gridSubsets>
  <metaWidthHeight>
    <int>4</int>
    <int>4</int>
  </metaWidthHeight>
  <expireCache>0</expireCache>
  <expireClients>0</expireClients>
  <parameterFilters>
    <styleParameterFilter>
      <key>STYLES</key>
      <defaultValue></defaultValue>
      <availableStyles class="sorted-set"/>
      <defaultStyle>jacobina:cad_secao_logradouro_l</defaultStyle>
    </styleParameterFilter>
  </parameterFilters>
  <gutter>0</gutter>
</GeoServerTileLayer>